{"v":"5.4.2","fr":60,"ip":0,"op":240,"w":600,"h":280,"nm":"888","ddd":0,"assets":[{"id":"image_0","w":604,"h":145,"u":"images/","p":"reward_888_img_0.png","e":0},{"id":"image_1","w":401,"h":201,"u":"images/","p":"reward_888_img_1.png","e":0},{"id":"image_2","w":29,"h":21,"u":"images/","p":"reward_888_img_2.png","e":0},{"id":"image_3","w":13,"h":13,"u":"images/","p":"reward_888_img_3.png","e":0},{"id":"image_4","w":26,"h":17,"u":"images/","p":"reward_888_img_4.png","e":0},{"id":"image_5","w":15,"h":15,"u":"images/","p":"reward_888_img_5.png","e":0},{"id":"image_6","w":29,"h":21,"u":"images/","p":"reward_888_img_6.png","e":0},{"id":"image_7","w":39,"h":45,"u":"images/","p":"reward_888_img_7.png","e":0},{"id":"image_8","w":58,"h":46,"u":"images/","p":"reward_888_img_8.png","e":0},{"id":"image_9","w":43,"h":39,"u":"images/","p":"reward_888_img_9.png","e":0},{"id":"image_10","w":52,"h":26,"u":"images/","p":"reward_888_img_10.png","e":0},{"id":"image_11","w":129,"h":102,"u":"images/","p":"reward_888_img_11.png","e":0},{"id":"comp_0","layers":[{"ddd":0,"ind":1,"ty":4,"nm":"Pink","sr":1,"ks":{"o":{"a":0,"k":100,"ix":11},"r":{"a":0,"k":0,"ix":10},"p":{"a":0,"k":[25,25,0],"ix":2},"a":{"a":0,"k":[0,0,0],"ix":1},"s":{"a":0,"k":[23,23,100],"ix":6}},"ao":0,"shapes":[{"d":1,"ty":"el","s":{"a":0,"k":[100,100],"ix":2},"p":{"a":0,"k":[0,0],"ix":3},"nm":"Ellipse 1","mn":"ADBE Vector Shape - Ellipse","hd":false},{"ty":"fl","c":{"a":0,"k":[0.965441176471,0.462444559733,0.629986751781,1],"ix":4},"o":{"a":0,"k":100,"ix":5},"r":1,"nm":"Fill 1","mn":"ADBE Vector Graphic - Fill","hd":false}],"ip":0,"op":1210,"st":0,"bm":0}]},{"id":"comp_1","layers":[{"ddd":0,"ind":1,"ty":4,"nm":"Orange","sr":1,"ks":{"o":{"a":0,"k":100,"ix":11},"r":{"a":0,"k":0,"ix":10},"p":{"a":0,"k":[25,25,0],"ix":2},"a":{"a":0,"k":[0,0,0],"ix":1},"s":{"a":0,"k":[23,23,100],"ix":6}},"ao":0,"shapes":[{"d":1,"ty":"el","s":{"a":0,"k":[100,100],"ix":2},"p":{"a":0,"k":[0,0],"ix":3},"nm":"Ellipse 1","mn":"ADBE Vector Shape - Ellipse","hd":false},{"ty":"fl","c":{"a":0,"k":[0.963204656863,0.55444467582,0.270045560949,1],"ix":4},"o":{"a":0,"k":100,"ix":5},"r":1,"nm":"Fill 1","mn":"ADBE Vector Graphic - Fill","hd":false}],"ip":0,"op":1210,"st":0,"bm":0}]},{"id":"comp_2","layers":[{"ddd":0,"ind":1,"ty":4,"nm":"Yellow","sr":1,"ks":{"o":{"a":0,"k":100,"ix":11},"r":{"a":0,"k":0,"ix":10},"p":{"a":0,"k":[25,25,0],"ix":2},"a":{"a":0,"k":[0,0,0],"ix":1},"s":{"a":0,"k":[11,11,100],"ix":6}},"ao":0,"shapes":[{"d":1,"ty":"el","s":{"a":0,"k":[100,100],"ix":2},"p":{"a":0,"k":[0,0],"ix":3},"nm":"Ellipse 1","mn":"ADBE Vector Shape - Ellipse","hd":false},{"ty":"fl","c":{"a":0,"k":[1,0.880851177141,0.355055147059,1],"ix":4},"o":{"a":0,"k":100,"ix":5},"r":1,"nm":"Fill 1","mn":"ADBE Vector Graphic - Fill","hd":false}],"ip":0,"op":1210,"st":0,"bm":0}]},{"id":"comp_3","layers":[{"ddd":0,"ind":1,"ty":4,"nm":"Blue","sr":1,"ks":{"o":{"a":0,"k":100,"ix":11},"r":{"a":0,"k":-40,"ix":10},"p":{"a":0,"k":[24.75,23.125,0],"ix":2},"a":{"a":0,"k":[0,0,0],"ix":1},"s":{"a":0,"k":[60,60,100],"ix":6}},"ao":0,"shapes":[{"ty":"gr","it":[{"ind":0,"ty":"sh","ix":1,"ks":{"a":0,"k":{"i":[[0,0],[0,0],[0,0],[0,0]],"o":[[0,0],[0,0],[0,0],[0,0]],"v":[[5.919,-13.012],[8.077,20.692],[-6.418,13.899],[-7.583,-20.115]],"c":true},"ix":2},"nm":"Path 1","mn":"ADBE Vector Shape - Group","hd":false},{"ty":"fl","c":{"a":0,"k":[0.403921568627,0.721568627451,0.945098039216,1],"ix":4},"o":{"a":0,"k":100,"ix":5},"r":1,"nm":"Fill 1","mn":"ADBE Vector Graphic - Fill","hd":false},{"ty":"tr","p":{"a":0,"k":[-1.779,4.339],"ix":2},"a":{"a":0,"k":[0,0],"ix":1},"s":{"a":0,"k":[100,100],"ix":3},"r":{"a":0,"k":0,"ix":6},"o":{"a":0,"k":100,"ix":7},"sk":{"a":0,"k":0,"ix":4},"sa":{"a":0,"k":0,"ix":5},"nm":"Transform"}],"nm":"Blue","np":2,"cix":2,"ix":1,"mn":"ADBE Vector Group","hd":false}],"ip":0,"op":1210,"st":0,"bm":0}]},{"id":"comp_4","layers":[{"ddd":0,"ind":1,"ty":4,"nm":"Green","sr":1,"ks":{"o":{"a":0,"k":100,"ix":11},"r":{"a":0,"k":218,"ix":10},"p":{"a":0,"k":[22,23.25,0],"ix":2},"a":{"a":0,"k":[0,0,0],"ix":1},"s":{"a":0,"k":[100,100,100],"ix":6}},"ao":0,"shapes":[{"ty":"gr","it":[{"ind":0,"ty":"sh","ix":1,"ks":{"a":0,"k":{"i":[[-5.875,11.25],[1.969,-0.062],[0,0],[-4.5,2.5]],"o":[[-7.5,-0.125],[-4.312,23.438],[0,0],[-11.75,-11.875]],"v":[[3.5,-16.625],[-15.812,-17.188],[-5.75,22.625],[8.375,17.375]],"c":true},"ix":2},"nm":"Path 1","mn":"ADBE Vector Shape - Group","hd":false},{"ty":"fl","c":{"a":0,"k":[0.501960784314,0.925490196078,0.501960784314,1],"ix":4},"o":{"a":0,"k":100,"ix":5},"r":1,"nm":"Fill 1","mn":"ADBE Vector Graphic - Fill","hd":false},{"ty":"tr","p":{"a":0,"k":[-0.125,0],"ix":2},"a":{"a":0,"k":[0,0],"ix":1},"s":{"a":0,"k":[100,100],"ix":3},"r":{"a":0,"k":0,"ix":6},"o":{"a":0,"k":100,"ix":7},"sk":{"a":0,"k":0,"ix":4},"sa":{"a":0,"k":0,"ix":5},"nm":"Transform"}],"nm":"Green","np":2,"cix":2,"ix":1,"mn":"ADBE Vector Group","hd":false}],"ip":0,"op":1210,"st":0,"bm":0}]},{"id":"comp_5","layers":[{"ddd":0,"ind":1,"ty":4,"nm":"Purple","sr":1,"ks":{"o":{"a":0,"k":100,"ix":11},"r":{"a":0,"k":218,"ix":10},"p":{"a":0,"k":[22,23.25,0],"ix":2},"a":{"a":0,"k":[0,0,0],"ix":1},"s":{"a":0,"k":[100,100,100],"ix":6}},"ao":0,"shapes":[{"ty":"gr","it":[{"ind":0,"ty":"sh","ix":1,"ks":{"a":0,"k":{"i":[[-5.875,11.25],[1.969,-0.062],[0,0],[-4.5,2.5]],"o":[[-7.5,-0.125],[-4.312,23.438],[0,0],[-11.75,-11.875]],"v":[[3.5,-16.625],[-15.812,-17.188],[-5.75,22.625],[8.375,17.375]],"c":true},"ix":2},"nm":"Path 1","mn":"ADBE Vector Shape - Group","hd":false},{"ty":"fl","c":{"a":0,"k":[0.639215686275,0.239215686275,0.996078431373,1],"ix":4},"o":{"a":0,"k":100,"ix":5},"r":1,"nm":"Fill 1","mn":"ADBE Vector Graphic - Fill","hd":false},{"ty":"tr","p":{"a":0,"k":[0,0],"ix":2},"a":{"a":0,"k":[0,0],"ix":1},"s":{"a":0,"k":[100,100],"ix":3},"r":{"a":0,"k":0,"ix":6},"o":{"a":0,"k":100,"ix":7},"sk":{"a":0,"k":0,"ix":4},"sa":{"a":0,"k":0,"ix":5},"nm":"Transform"}],"nm":"Purple","np":2,"cix":2,"ix":1,"mn":"ADBE Vector Group","hd":false}],"ip":0,"op":1210,"st":0,"bm":0}]},{"id":"comp_6","layers":[{"ddd":0,"ind":1,"ty":4,"nm":"Blue","sr":1,"ks":{"o":{"a":0,"k":100,"ix":11},"r":{"a":0,"k":218,"ix":10},"p":{"a":0,"k":[22,23.25,0],"ix":2},"a":{"a":0,"k":[0,0,0],"ix":1},"s":{"a":0,"k":[100,100,100],"ix":6}},"ao":0,"shapes":[{"ty":"gr","it":[{"ind":0,"ty":"sh","ix":1,"ks":{"a":0,"k":{"i":[[-5.875,11.25],[1.969,-0.062],[0,0],[-4.5,2.5]],"o":[[-7.5,-0.125],[-4.312,23.438],[0,0],[-11.75,-11.875]],"v":[[3.5,-16.625],[-15.812,-17.188],[-5.75,22.625],[8.375,17.375]],"c":true},"ix":2},"nm":"Path 1","mn":"ADBE Vector Shape - Group","hd":false},{"ty":"fl","c":{"a":0,"k":[0.403921568627,0.721568627451,0.945098039216,1],"ix":4},"o":{"a":0,"k":100,"ix":5},"r":1,"nm":"Fill 1","mn":"ADBE Vector Graphic - Fill","hd":false},{"ty":"tr","p":{"a":0,"k":[0,0],"ix":2},"a":{"a":0,"k":[0,0],"ix":1},"s":{"a":0,"k":[100,100],"ix":3},"r":{"a":0,"k":0,"ix":6},"o":{"a":0,"k":100,"ix":7},"sk":{"a":0,"k":0,"ix":4},"sa":{"a":0,"k":0,"ix":5},"nm":"Transform"}],"nm":"Blue","np":2,"cix":2,"ix":1,"mn":"ADBE Vector Group","hd":false}],"ip":0,"op":1210,"st":0,"bm":0}]}],"layers":[{"ddd":0,"ind":1,"ty":2,"nm":"anim_num_end.png","cl":"png","refId":"image_0","sr":1,"ks":{"o":{"a":1,"k":[{"i":{"x":[0.999],"y":[1]},"o":{"x":[0.42],"y":[0]},"n":["0p999_1_0p42_0"],"t":90,"s":[0],"e":[100]},{"i":{"x":[0.833],"y":[0.833]},"o":{"x":[0.167],"y":[0.167]},"n":["0p833_0p833_0p167_0p167"],"t":104,"s":[100],"e":[100]},{"t":149}],"ix":11},"r":{"a":0,"k":0,"ix":10},"p":{"a":0,"k":[273,216.1,0],"ix":2},"a":{"a":0,"k":[302,72.5,0],"ix":1},"s":{"a":1,"k":[{"i":{"x":[0.633,0.633,0.667],"y":[1,1,1]},"o":{"x":[0.42,0.42,0.42],"y":[0,0,0]},"n":["0p633_1_0p42_0","0p633_1_0p42_0","0p667_1_0p42_0"],"t":90,"s":[97,97,100],"e":[60,60,100]},{"i":{"x":[0.634,0.634,0.667],"y":[1,1,1]},"o":{"x":[0.586,0.586,0.333],"y":[0,0,0]},"n":["0p634_1_0p586_0","0p634_1_0p586_0","0p667_1_0p333_0"],"t":104,"s":[60,60,100],"e":[62,62,100]},{"i":{"x":[0.469,0.469,0.667],"y":[1,1,1]},"o":{"x":[0.4,0.4,0.333],"y":[0,0,0]},"n":["0p469_1_0p4_0","0p469_1_0p4_0","0p667_1_0p333_0"],"t":112,"s":[62,62,100],"e":[60,60,100]},{"i":{"x":[0.833,0.833,0.833],"y":[1,1,1]},"o":{"x":[0.333,0.333,0.333],"y":[0,0,0]},"n":["0p833_1_0p333_0","0p833_1_0p333_0","0p833_1_0p333_0"],"t":118,"s":[60,60,100],"e":[60,60,100]},{"t":149}],"ix":6}},"ao":0,"ip":0,"op":240,"st":0,"bm":0},{"ddd":0,"ind":2,"ty":4,"nm":"Group 2","sr":1,"ks":{"o":{"a":0,"k":100,"ix":11},"r":{"a":1,"k":[{"i":{"x":[0.58],"y":[1]},"o":{"x":[0.001],"y":[0]},"n":["0p58_1_0p001_0"],"t":90,"s":[0],"e":[4]},{"t":99}],"ix":10},"p":{"a":1,"k":[{"i":{"x":0.833,"y":0.833},"o":{"x":0.167,"y":0.167},"n":"0p833_0p833_0p167_0p167","t":30,"s":[300,140,0],"e":[300,140,0],"to":[0,0,0],"ti":[0,0,0]},{"i":{"x":0.58,"y":1},"o":{"x":0.001,"y":0},"n":"0p58_1_0p001_0","t":90,"s":[300,140,0],"e":[296,78,0],"to":[-0.66666668653488,-10.3333330154419,0],"ti":[0.66666668653488,10.3333330154419,0]},{"t":99}],"ix":2},"a":{"a":0,"k":[0,0,0],"ix":1},"s":{"a":1,"k":[{"i":{"x":[0.833,0.833,0.833],"y":[0.833,0.833,0.833]},"o":{"x":[0.167,0.167,0.167],"y":[0.167,0.167,0.167]},"n":["0p833_0p833_0p167_0p167","0p833_0p833_0p167_0p167","0p833_0p833_0p167_0p167"],"t":30,"s":[100,100,100],"e":[100,100,100]},{"i":{"x":[0.58,0.58,0.58],"y":[1,1,1]},"o":{"x":[0.001,0.001,0.001],"y":[0,0,0]},"n":["0p58_1_0p001_0","0p58_1_0p001_0","0p58_1_0p001_0"],"t":90,"s":[100,100,100],"e":[90,90,100]},{"t":99}],"ix":6}},"ao":0,"shapes":[{"ty":"gr","it":[{"ty":"rc","d":1,"s":{"a":0,"k":[600,280],"ix":2},"p":{"a":0,"k":[0,0],"ix":3},"r":{"a":0,"k":0,"ix":4},"nm":"Rectangle Path 1","mn":"ADBE Vector Shape - Rect","hd":false},{"ty":"tr","p":{"a":0,"k":[0,0],"ix":2},"a":{"a":0,"k":[0,0],"ix":1},"s":{"a":0,"k":[100,100],"ix":3},"r":{"a":0,"k":0,"ix":6},"o":{"a":0,"k":100,"ix":7},"sk":{"a":0,"k":0,"ix":4},"sa":{"a":0,"k":0,"ix":5},"nm":"Transform"}],"nm":"Rectangle 1","np":1,"cix":2,"ix":1,"mn":"ADBE Vector Group","hd":false}],"ip":0,"op":240,"st":0,"bm":0},{"ddd":0,"ind":3,"ty":2,"nm":"anim_num_888.png","cl":"png","parent":2,"refId":"image_1","sr":1,"ks":{"o":{"a":1,"k":[{"i":{"x":[0.833],"y":[0.833]},"o":{"x":[0.167],"y":[0.167]},"n":["0p833_0p833_0p167_0p167"],"t":0,"s":[0],"e":[100]},{"t":7}],"ix":11},"r":{"a":0,"k":-5,"ix":10},"p":{"a":1,"k":[{"i":{"x":0.48,"y":1},"o":{"x":0.26,"y":0.957},"n":"0p48_1_0p26_0p957","t":0,"s":[-81,31.25,0],"e":[-91,31,0],"to":[-1.66666662693024,-0.04166666790843,0],"ti":[1.66666662693024,0.04166666790843,0]},{"t":12}],"ix":2},"a":{"a":0,"k":[200.5,100.5,0],"ix":1},"s":{"a":1,"k":[{"i":{"x":[0.354,0.354,0.667],"y":[0.991,0.991,1]},"o":{"x":[0.06,0.06,0.167],"y":[0.12,0.12,0]},"n":["0p354_0p991_0p06_0p12","0p354_0p991_0p06_0p12","0p667_1_0p167_0"],"t":0,"s":[80,80,100],"e":[105,105,100]},{"i":{"x":[0.592,0.592,0.833],"y":[0.955,0.955,1]},"o":{"x":[0.659,0.659,0.167],"y":[0.013,0.013,0]},"n":["0p592_0p955_0p659_0p013","0p592_0p955_0p659_0p013","0p833_1_0p167_0"],"t":12,"s":[105,105,100],"e":[98,98,100]},{"i":{"x":[0.384,0.384,0.833],"y":[0.869,0.869,1]},"o":{"x":[0.883,0.883,0.167],"y":[-0.003,-0.003,0]},"n":["0p384_0p869_0p883_-0p003","0p384_0p869_0p883_-0p003","0p833_1_0p167_0"],"t":22,"s":[98,98,100],"e":[100,100,100]},{"t":27}],"ix":6}},"ao":0,"ip":0,"op":240,"st":0,"bm":0},{"ddd":0,"ind":4,"ty":4,"nm":"Group 1","parent":2,"sr":1,"ks":{"o":{"a":0,"k":100,"ix":11},"r":{"a":0,"k":0,"ix":10},"p":{"a":0,"k":[160,0,0],"ix":2},"a":{"a":0,"k":[0,0,0],"ix":1},"s":{"a":0,"k":[100,100,100],"ix":6}},"ao":0,"shapes":[{"ty":"gr","it":[{"ty":"rc","d":1,"s":{"a":0,"k":[280,280],"ix":2},"p":{"a":0,"k":[0,0],"ix":3},"r":{"a":0,"k":0,"ix":4},"nm":"Rectangle Path 1","mn":"ADBE Vector Shape - Rect","hd":false},{"ty":"tr","p":{"a":0,"k":[0,0],"ix":2},"a":{"a":0,"k":[0,0],"ix":1},"s":{"a":0,"k":[100,100],"ix":3},"r":{"a":0,"k":0,"ix":6},"o":{"a":0,"k":100,"ix":7},"sk":{"a":0,"k":0,"ix":4},"sa":{"a":0,"k":0,"ix":5},"nm":"Transform"}],"nm":"Rectangle 1","np":1,"cix":2,"ix":1,"mn":"ADBE Vector Group","hd":false}],"ip":0,"op":240,"st":0,"bm":0},{"ddd":0,"ind":5,"ty":0,"nm":"1","parent":4,"refId":"comp_0","sr":1,"ks":{"o":{"a":1,"k":[{"i":{"x":[0.833],"y":[0.833]},"o":{"x":[0.167],"y":[0.167]},"n":["0p833_0p833_0p167_0p167"],"t":36,"s":[0],"e":[100]},{"t":46}],"ix":11},"r":{"a":1,"k":[{"i":{"x":[0.833],"y":[0.833]},"o":{"x":[0.167],"y":[0.167]},"n":["0p833_0p833_0p167_0p167"],"t":31,"s":[-50],"e":[30]},{"t":137}],"ix":10},"p":{"a":1,"k":[{"i":{"x":0.48,"y":1},"o":{"x":0.171,"y":1},"n":"0p48_1_0p171_1","t":31,"s":[0,0,0],"e":[-97.5,-18.5,0],"to":[6.91666650772095,-64.8333358764648,0],"ti":[32.5833320617676,-36.6666679382324,0]},{"t":137}],"ix":2},"a":{"a":0,"k":[25,25,0],"ix":1},"s":{"a":1,"k":[{"i":{"x":[0.833,0.833,0.833],"y":[0.833,0.833,0.833]},"o":{"x":[0.167,0.167,0.167],"y":[0.167,0.167,0.167]},"n":["0p833_0p833_0p167_0p167","0p833_0p833_0p167_0p167","0p833_0p833_0p167_0p167"],"t":44,"s":[80,80,100],"e":[0,0,100]},{"t":137}],"ix":6}},"ao":0,"w":50,"h":50,"ip":31,"op":1241,"st":31,"bm":0},{"ddd":0,"ind":6,"ty":0,"nm":"2","parent":4,"refId":"comp_1","sr":1,"ks":{"o":{"a":1,"k":[{"i":{"x":[0.833],"y":[0.833]},"o":{"x":[0.167],"y":[0.167]},"n":["0p833_0p833_0p167_0p167"],"t":54,"s":[0],"e":[100]},{"t":64}],"ix":11},"r":{"a":1,"k":[{"i":{"x":[0.833],"y":[0.833]},"o":{"x":[0.167],"y":[0.167]},"n":["0p833_0p833_0p167_0p167"],"t":49,"s":[0],"e":[20]},{"t":155}],"ix":10},"p":{"a":1,"k":[{"i":{"x":0.48,"y":1},"o":{"x":0.246,"y":1},"n":"0p48_1_0p246_1","t":49,"s":[0,0,0],"e":[-102.5,54.5,0],"to":[-48.8333320617676,-16.9166660308838,0],"ti":[20.3333339691162,-72.5833358764648,0]},{"t":155}],"ix":2},"a":{"a":0,"k":[25,25,0],"ix":1},"s":{"a":1,"k":[{"i":{"x":[0.833,0.833,0.833],"y":[0.833,0.833,0.833]},"o":{"x":[0.167,0.167,0.167],"y":[0.167,0.167,0.167]},"n":["0p833_0p833_0p167_0p167","0p833_0p833_0p167_0p167","0p833_0p833_0p167_0p167"],"t":62,"s":[50,50,100],"e":[0,0,100]},{"t":155}],"ix":6}},"ao":0,"w":50,"h":50,"ip":49,"op":1259,"st":49,"bm":0},{"ddd":0,"ind":7,"ty":0,"nm":"3","parent":4,"refId":"comp_2","sr":1,"ks":{"o":{"a":1,"k":[{"i":{"x":[0.833],"y":[0.833]},"o":{"x":[0.167],"y":[0.167]},"n":["0p833_0p833_0p167_0p167"],"t":71,"s":[0],"e":[100]},{"t":81}],"ix":11},"r":{"a":1,"k":[{"i":{"x":[0.833],"y":[0.833]},"o":{"x":[0.167],"y":[0.167]},"n":["0p833_0p833_0p167_0p167"],"t":66,"s":[90],"e":[-30]},{"t":172}],"ix":10},"p":{"a":1,"k":[{"i":{"x":0.48,"y":1},"o":{"x":0.19,"y":1},"n":"0p48_1_0p19_1","t":66,"s":[0,0,0],"e":[87,-3.5,0],"to":[25.5833339691162,-52,0],"ti":[-13.0833330154419,-40.5,0]},{"t":172}],"ix":2},"a":{"a":0,"k":[25,25,0],"ix":1},"s":{"a":1,"k":[{"i":{"x":[0.833,0.833,0.833],"y":[0.833,0.833,0.833]},"o":{"x":[0.167,0.167,0.167],"y":[0.167,0.167,0.167]},"n":["0p833_0p833_0p167_0p167","0p833_0p833_0p167_0p167","0p833_0p833_0p167_0p167"],"t":79,"s":[80,80,100],"e":[0,0,100]},{"t":172}],"ix":6}},"ao":0,"w":50,"h":50,"ip":66,"op":1276,"st":66,"bm":0},{"ddd":0,"ind":8,"ty":0,"nm":"5","parent":4,"refId":"comp_3","sr":1,"ks":{"o":{"a":1,"k":[{"i":{"x":[0.833],"y":[0.833]},"o":{"x":[0.167],"y":[0.167]},"n":["0p833_0p833_0p167_0p167"],"t":64,"s":[0],"e":[100]},{"t":74}],"ix":11},"r":{"a":1,"k":[{"i":{"x":[0.833],"y":[0.833]},"o":{"x":[0.167],"y":[0.167]},"n":["0p833_0p833_0p167_0p167"],"t":59,"s":[0],"e":[0]},{"t":165}],"ix":10},"p":{"a":1,"k":[{"i":{"x":0.48,"y":1},"o":{"x":0.181,"y":1},"n":"0p48_1_0p181_1","t":59,"s":[0,0,0],"e":[-80,-71,0],"to":[-37.5,-8.41666698455811,0],"ti":[52.5,12.4166669845581,0]},{"t":165}],"ix":2},"a":{"a":0,"k":[25,25,0],"ix":1},"s":{"a":1,"k":[{"i":{"x":[0.833,0.833,0.833],"y":[0.833,0.833,0.833]},"o":{"x":[0.167,0.167,0.167],"y":[0.167,0.167,0.167]},"n":["0p833_0p833_0p167_0p167","0p833_0p833_0p167_0p167","0p833_0p833_0p167_0p167"],"t":72,"s":[80,80,100],"e":[0,0,100]},{"t":165}],"ix":6}},"ao":0,"w":50,"h":50,"ip":59,"op":1269,"st":59,"bm":0},{"ddd":0,"ind":9,"ty":0,"nm":"3","parent":4,"refId":"comp_4","sr":1,"ks":{"o":{"a":1,"k":[{"i":{"x":[0.833],"y":[0.833]},"o":{"x":[0.167],"y":[0.167]},"n":["0p833_0p833_0p167_0p167"],"t":79,"s":[0],"e":[100]},{"t":89}],"ix":11},"r":{"a":1,"k":[{"i":{"x":[0.833],"y":[0.833]},"o":{"x":[0.167],"y":[0.167]},"n":["0p833_0p833_0p167_0p167"],"t":74,"s":[50],"e":[-15]},{"t":180}],"ix":10},"p":{"a":1,"k":[{"i":{"x":0.48,"y":1},"o":{"x":0.159,"y":1},"n":"0p48_1_0p159_1","t":74,"s":[0,0,0],"e":[-62,-67.5,0],"to":[-0.66666668653488,-44.3333320617676,0],"ti":[52.75,3.83333325386047,0]},{"t":180}],"ix":2},"a":{"a":0,"k":[25,25,0],"ix":1},"s":{"a":1,"k":[{"i":{"x":[0.833,0.833,0.833],"y":[0.833,0.833,0.833]},"o":{"x":[0.167,0.167,0.167],"y":[0.167,0.167,0.167]},"n":["0p833_0p833_0p167_0p167","0p833_0p833_0p167_0p167","0p833_0p833_0p167_0p167"],"t":87,"s":[80,80,100],"e":[0,0,100]},{"t":180}],"ix":6}},"ao":0,"w":50,"h":50,"ip":74,"op":1284,"st":74,"bm":0},{"ddd":0,"ind":10,"ty":0,"nm":"4","parent":4,"refId":"comp_5","sr":1,"ks":{"o":{"a":1,"k":[{"i":{"x":[0.833],"y":[0.833]},"o":{"x":[0.167],"y":[0.167]},"n":["0p833_0p833_0p167_0p167"],"t":42,"s":[0],"e":[100]},{"t":52}],"ix":11},"r":{"a":1,"k":[{"i":{"x":[0.833],"y":[0.833]},"o":{"x":[0.167],"y":[0.167]},"n":["0p833_0p833_0p167_0p167"],"t":37,"s":[0],"e":[0]},{"t":143}],"ix":10},"p":{"a":1,"k":[{"i":{"x":0.48,"y":1},"o":{"x":0.26,"y":0.985},"n":"0p48_1_0p26_0p985","t":37,"s":[0,0,0],"e":[-64.25,75.75,0],"to":[-48.2083320617676,-74.4583358764648,0],"ti":[-33.7916679382324,-73.0416641235352,0]},{"t":143}],"ix":2},"a":{"a":0,"k":[25,25,0],"ix":1},"s":{"a":1,"k":[{"i":{"x":[0.833,0.833,0.833],"y":[0.833,0.833,0.833]},"o":{"x":[0.167,0.167,0.167],"y":[0.167,0.167,0.167]},"n":["0p833_0p833_0p167_0p167","0p833_0p833_0p167_0p167","0p833_0p833_0p167_0p167"],"t":50,"s":[80,80,100],"e":[0,0,100]},{"t":143}],"ix":6}},"ao":0,"w":50,"h":50,"ip":37,"op":1247,"st":37,"bm":0},{"ddd":0,"ind":11,"ty":0,"nm":"5","parent":4,"refId":"comp_6","sr":1,"ks":{"o":{"a":1,"k":[{"i":{"x":[0.833],"y":[0.833]},"o":{"x":[0.167],"y":[0.167]},"n":["0p833_0p833_0p167_0p167"],"t":31,"s":[0],"e":[100]},{"t":41}],"ix":11},"r":{"a":1,"k":[{"i":{"x":[0.833],"y":[0.833]},"o":{"x":[0.167],"y":[0.167]},"n":["0p833_0p833_0p167_0p167"],"t":26,"s":[0],"e":[0]},{"t":132}],"ix":10},"p":{"a":1,"k":[{"i":{"x":0.48,"y":1},"o":{"x":0.246,"y":1},"n":"0p48_1_0p246_1","t":26,"s":[0,0,0],"e":[117,82.5,0],"to":[76.0833358764648,-53.9166679382324,0],"ti":[-49.5833320617676,-6.08333349227905,0]},{"t":132}],"ix":2},"a":{"a":0,"k":[25,25,0],"ix":1},"s":{"a":1,"k":[{"i":{"x":[0.833,0.833,0.833],"y":[0.833,0.833,0.833]},"o":{"x":[0.167,0.167,0.167],"y":[0.167,0.167,0.167]},"n":["0p833_0p833_0p167_0p167","0p833_0p833_0p167_0p167","0p833_0p833_0p167_0p167"],"t":39,"s":[80,80,100],"e":[0,0,100]},{"t":132}],"ix":6}},"ao":0,"w":50,"h":50,"ip":26,"op":1236,"st":26,"bm":0},{"ddd":0,"ind":12,"ty":0,"nm":"1","parent":4,"refId":"comp_0","sr":1,"ks":{"o":{"a":1,"k":[{"i":{"x":[0.833],"y":[0.833]},"o":{"x":[0.167],"y":[0.167]},"n":["0p833_0p833_0p167_0p167"],"t":15,"s":[0],"e":[100]},{"t":25}],"ix":11},"r":{"a":1,"k":[{"i":{"x":[0.833],"y":[0.833]},"o":{"x":[0.167],"y":[0.167]},"n":["0p833_0p833_0p167_0p167"],"t":10,"s":[-50],"e":[30]},{"t":116}],"ix":10},"p":{"a":1,"k":[{"i":{"x":0.48,"y":1},"o":{"x":0.211,"y":1},"n":"0p48_1_0p211_1","t":10,"s":[0,0,0],"e":[126,-104,0],"to":[27.9166660308838,-50.3333320617676,0],"ti":[-14.9166669845581,77.3333358764648,0]},{"t":116}],"ix":2},"a":{"a":0,"k":[25,25,0],"ix":1},"s":{"a":1,"k":[{"i":{"x":[0.833,0.833,0.833],"y":[0.833,0.833,0.833]},"o":{"x":[0.167,0.167,0.167],"y":[0.167,0.167,0.167]},"n":["0p833_0p833_0p167_0p167","0p833_0p833_0p167_0p167","0p833_0p833_0p167_0p167"],"t":23,"s":[80,80,100],"e":[0,0,100]},{"t":116}],"ix":6}},"ao":0,"w":50,"h":50,"ip":10,"op":1220,"st":10,"bm":0},{"ddd":0,"ind":13,"ty":0,"nm":"2","parent":4,"refId":"comp_1","sr":1,"ks":{"o":{"a":1,"k":[{"i":{"x":[0.833],"y":[0.833]},"o":{"x":[0.167],"y":[0.167]},"n":["0p833_0p833_0p167_0p167"],"t":33,"s":[0],"e":[100]},{"t":43}],"ix":11},"r":{"a":1,"k":[{"i":{"x":[0.833],"y":[0.833]},"o":{"x":[0.167],"y":[0.167]},"n":["0p833_0p833_0p167_0p167"],"t":28,"s":[0],"e":[20]},{"t":134}],"ix":10},"p":{"a":1,"k":[{"i":{"x":0.48,"y":1},"o":{"x":0.186,"y":1},"n":"0p48_1_0p186_1","t":28,"s":[0,0,0],"e":[92.5,-41,0],"to":[28.1666660308838,-43.4166679382324,0],"ti":[-31.1666660308838,24.9166660308838,0]},{"t":134}],"ix":2},"a":{"a":0,"k":[25,25,0],"ix":1},"s":{"a":1,"k":[{"i":{"x":[0.833,0.833,0.833],"y":[0.833,0.833,0.833]},"o":{"x":[0.167,0.167,0.167],"y":[0.167,0.167,0.167]},"n":["0p833_0p833_0p167_0p167","0p833_0p833_0p167_0p167","0p833_0p833_0p167_0p167"],"t":41,"s":[50,50,100],"e":[0,0,100]},{"t":134}],"ix":6}},"ao":0,"w":50,"h":50,"ip":28,"op":1238,"st":28,"bm":0},{"ddd":0,"ind":14,"ty":0,"nm":"3","parent":4,"refId":"comp_2","sr":1,"ks":{"o":{"a":1,"k":[{"i":{"x":[0.833],"y":[0.833]},"o":{"x":[0.167],"y":[0.167]},"n":["0p833_0p833_0p167_0p167"],"t":50,"s":[0],"e":[100]},{"t":60}],"ix":11},"r":{"a":1,"k":[{"i":{"x":[0.833],"y":[0.833]},"o":{"x":[0.167],"y":[0.167]},"n":["0p833_0p833_0p167_0p167"],"t":45,"s":[90],"e":[-30]},{"t":151}],"ix":10},"p":{"a":1,"k":[{"i":{"x":0.48,"y":1},"o":{"x":0.259,"y":1},"n":"0p48_1_0p259_1","t":45,"s":[0,0,0],"e":[105.5,-108,0],"to":[25.5833339691162,-52,0],"ti":[3.91666674613953,73.5,0]},{"t":151}],"ix":2},"a":{"a":0,"k":[25,25,0],"ix":1},"s":{"a":1,"k":[{"i":{"x":[0.833,0.833,0.833],"y":[0.833,0.833,0.833]},"o":{"x":[0.167,0.167,0.167],"y":[0.167,0.167,0.167]},"n":["0p833_0p833_0p167_0p167","0p833_0p833_0p167_0p167","0p833_0p833_0p167_0p167"],"t":58,"s":[80,80,100],"e":[0,0,100]},{"t":151}],"ix":6}},"ao":0,"w":50,"h":50,"ip":45,"op":1255,"st":45,"bm":0},{"ddd":0,"ind":15,"ty":0,"nm":"5","parent":4,"refId":"comp_3","sr":1,"ks":{"o":{"a":1,"k":[{"i":{"x":[0.833],"y":[0.833]},"o":{"x":[0.167],"y":[0.167]},"n":["0p833_0p833_0p167_0p167"],"t":43,"s":[0],"e":[100]},{"t":53}],"ix":11},"r":{"a":1,"k":[{"i":{"x":[0.833],"y":[0.833]},"o":{"x":[0.167],"y":[0.167]},"n":["0p833_0p833_0p167_0p167"],"t":38,"s":[0],"e":[0]},{"t":144}],"ix":10},"p":{"a":1,"k":[{"i":{"x":0.48,"y":1},"o":{"x":0.208,"y":1},"n":"0p48_1_0p208_1","t":38,"s":[0,0,0],"e":[5,-119,0],"to":[7,-39.9166679382324,0],"ti":[39,40.4166679382324,0]},{"t":144}],"ix":2},"a":{"a":0,"k":[25,25,0],"ix":1},"s":{"a":1,"k":[{"i":{"x":[0.833,0.833,0.833],"y":[0.833,0.833,0.833]},"o":{"x":[0.167,0.167,0.167],"y":[0.167,0.167,0.167]},"n":["0p833_0p833_0p167_0p167","0p833_0p833_0p167_0p167","0p833_0p833_0p167_0p167"],"t":51,"s":[80,80,100],"e":[0,0,100]},{"t":144}],"ix":6}},"ao":0,"w":50,"h":50,"ip":38,"op":1248,"st":38,"bm":0},{"ddd":0,"ind":16,"ty":0,"nm":"3","parent":4,"refId":"comp_4","sr":1,"ks":{"o":{"a":1,"k":[{"i":{"x":[0.833],"y":[0.833]},"o":{"x":[0.167],"y":[0.167]},"n":["0p833_0p833_0p167_0p167"],"t":58,"s":[0],"e":[100]},{"t":68}],"ix":11},"r":{"a":1,"k":[{"i":{"x":[0.833],"y":[0.833]},"o":{"x":[0.167],"y":[0.167]},"n":["0p833_0p833_0p167_0p167"],"t":53,"s":[50],"e":[-15]},{"t":159}],"ix":10},"p":{"a":1,"k":[{"i":{"x":0.48,"y":1},"o":{"x":0.198,"y":1},"n":"0p48_1_0p198_1","t":53,"s":[0,0,0],"e":[44,-104,0],"to":[-0.66666668653488,-44.3333320617676,0],"ti":[51.25,47.8333320617676,0]},{"t":159}],"ix":2},"a":{"a":0,"k":[25,25,0],"ix":1},"s":{"a":1,"k":[{"i":{"x":[0.833,0.833,0.833],"y":[0.833,0.833,0.833]},"o":{"x":[0.167,0.167,0.167],"y":[0.167,0.167,0.167]},"n":["0p833_0p833_0p167_0p167","0p833_0p833_0p167_0p167","0p833_0p833_0p167_0p167"],"t":66,"s":[80,80,100],"e":[0,0,100]},{"t":159}],"ix":6}},"ao":0,"w":50,"h":50,"ip":53,"op":1263,"st":53,"bm":0},{"ddd":0,"ind":17,"ty":0,"nm":"4","parent":4,"refId":"comp_5","sr":1,"ks":{"o":{"a":1,"k":[{"i":{"x":[0.833],"y":[0.833]},"o":{"x":[0.167],"y":[0.167]},"n":["0p833_0p833_0p167_0p167"],"t":21,"s":[0],"e":[100]},{"t":31}],"ix":11},"r":{"a":1,"k":[{"i":{"x":[0.833],"y":[0.833]},"o":{"x":[0.167],"y":[0.167]},"n":["0p833_0p833_0p167_0p167"],"t":16,"s":[0],"e":[0]},{"t":122}],"ix":10},"p":{"a":1,"k":[{"i":{"x":0.48,"y":1},"o":{"x":0.222,"y":1},"n":"0p48_1_0p222_1","t":16,"s":[0,0,0],"e":[124.25,37.25,0],"to":[25.7916660308838,-21.9583339691162,0],"ti":[-40.2916679382324,-68.0416641235352,0]},{"t":122}],"ix":2},"a":{"a":0,"k":[25,25,0],"ix":1},"s":{"a":1,"k":[{"i":{"x":[0.833,0.833,0.833],"y":[0.833,0.833,0.833]},"o":{"x":[0.167,0.167,0.167],"y":[0.167,0.167,0.167]},"n":["0p833_0p833_0p167_0p167","0p833_0p833_0p167_0p167","0p833_0p833_0p167_0p167"],"t":29,"s":[80,80,100],"e":[0,0,100]},{"t":122}],"ix":6}},"ao":0,"w":50,"h":50,"ip":16,"op":1226,"st":16,"bm":0},{"ddd":0,"ind":18,"ty":0,"nm":"5","parent":4,"refId":"comp_6","sr":1,"ks":{"o":{"a":1,"k":[{"i":{"x":[0.833],"y":[0.833]},"o":{"x":[0.167],"y":[0.167]},"n":["0p833_0p833_0p167_0p167"],"t":10,"s":[0],"e":[100]},{"t":20}],"ix":11},"r":{"a":1,"k":[{"i":{"x":[0.833],"y":[0.833]},"o":{"x":[0.167],"y":[0.167]},"n":["0p833_0p833_0p167_0p167"],"t":5,"s":[0],"e":[0]},{"t":111}],"ix":10},"p":{"a":1,"k":[{"i":{"x":0.48,"y":1},"o":{"x":0.203,"y":1},"n":"0p48_1_0p203_1","t":5,"s":[0,0,0],"e":[-26,-130.5,0],"to":[-10.9166669845581,-68.4166641235352,0],"ti":[44.9166679382324,32.9166679382324,0]},{"t":111}],"ix":2},"a":{"a":0,"k":[25,25,0],"ix":1},"s":{"a":1,"k":[{"i":{"x":[0.833,0.833,0.833],"y":[0.833,0.833,0.833]},"o":{"x":[0.167,0.167,0.167],"y":[0.167,0.167,0.167]},"n":["0p833_0p833_0p167_0p167","0p833_0p833_0p167_0p167","0p833_0p833_0p167_0p167"],"t":18,"s":[80,80,100],"e":[0,0,100]},{"t":111}],"ix":6}},"ao":0,"w":50,"h":50,"ip":5,"op":1215,"st":5,"bm":0},{"ddd":0,"ind":19,"ty":2,"nm":"9.png","cl":"png","parent":4,"refId":"image_2","sr":1,"ks":{"o":{"a":1,"k":[{"i":{"x":[0.833],"y":[0.833]},"o":{"x":[0.167],"y":[0.167]},"n":["0p833_0p833_0p167_0p167"],"t":0,"s":[0],"e":[100]},{"i":{"x":[0.833],"y":[0.833]},"o":{"x":[0.167],"y":[0.167]},"n":["0p833_0p833_0p167_0p167"],"t":10,"s":[100],"e":[100]},{"i":{"x":[0.833],"y":[0.833]},"o":{"x":[0.167],"y":[0.167]},"n":["0p833_0p833_0p167_0p167"],"t":85,"s":[100],"e":[0]},{"t":96}],"ix":11},"r":{"a":0,"k":0,"ix":10},"p":{"a":1,"k":[{"i":{"x":0.48,"y":1},"o":{"x":0.26,"y":0.461},"n":"0p48_1_0p26_0p461","t":0,"s":[-7.405,-2.916,0],"e":[-70.25,-114.5,0],"to":[-20.1407928466797,-26.8472576141357,0],"ti":[63.9741249084473,23.0555896759033,0]},{"t":96}],"ix":2},"a":{"a":0,"k":[14.5,10.5,0],"ix":1},"s":{"a":0,"k":[100,100,100],"ix":6}},"ao":0,"ip":0,"op":240,"st":0,"bm":0},{"ddd":0,"ind":20,"ty":2,"nm":"11.png","cl":"png","parent":4,"refId":"image_3","sr":1,"ks":{"o":{"a":1,"k":[{"i":{"x":[0.833],"y":[0.833]},"o":{"x":[0.167],"y":[0.167]},"n":["0p833_0p833_0p167_0p167"],"t":34,"s":[0],"e":[100]},{"i":{"x":[0.833],"y":[0.833]},"o":{"x":[0.167],"y":[0.167]},"n":["0p833_0p833_0p167_0p167"],"t":44,"s":[100],"e":[100]},{"i":{"x":[0.833],"y":[0.833]},"o":{"x":[0.167],"y":[0.167]},"n":["0p833_0p833_0p167_0p167"],"t":114,"s":[100],"e":[0]},{"t":125}],"ix":11},"r":{"a":0,"k":0,"ix":10},"p":{"a":1,"k":[{"i":{"x":0.48,"y":1},"o":{"x":0.26,"y":0.906},"n":"0p48_1_0p26_0p906","t":34,"s":[25.599,-10.158,0],"e":[93.5,-126.5,0],"to":[4.90012884140015,-53.6403121948242,0],"ti":[-14.5667953491211,50.5569801330566,0]},{"t":125}],"ix":2},"a":{"a":0,"k":[6.5,6.5,0],"ix":1},"s":{"a":1,"k":[{"i":{"x":[0.058,0.058,0.667],"y":[1,1,1]},"o":{"x":[0,0,0.333],"y":[0,0,0]},"n":["0p058_1_0_0","0p058_1_0_0","0p667_1_0p333_0"],"t":34,"s":[0,0,100],"e":[100,100,100]},{"i":{"x":[1,1,0.667],"y":[1,1,1]},"o":{"x":[0.809,0.809,0.333],"y":[0,0,0]},"n":["1_1_0p809_0","1_1_0p809_0","0p667_1_0p333_0"],"t":66,"s":[100,100,100],"e":[0,0,100]},{"t":127}],"ix":6}},"ao":0,"ip":21,"op":240,"st":21,"bm":0},{"ddd":0,"ind":21,"ty":2,"nm":"12.png","cl":"png","parent":4,"refId":"image_4","sr":1,"ks":{"o":{"a":1,"k":[{"i":{"x":[0.833],"y":[0.833]},"o":{"x":[0.167],"y":[0.167]},"n":["0p833_0p833_0p167_0p167"],"t":22,"s":[0],"e":[100]},{"i":{"x":[0.833],"y":[0.833]},"o":{"x":[0.167],"y":[0.167]},"n":["0p833_0p833_0p167_0p167"],"t":32,"s":[100],"e":[100]},{"i":{"x":[0.833],"y":[0.833]},"o":{"x":[0.167],"y":[0.167]},"n":["0p833_0p833_0p167_0p167"],"t":102,"s":[100],"e":[0]},{"t":113}],"ix":11},"r":{"a":0,"k":0,"ix":10},"p":{"a":1,"k":[{"i":{"x":0.48,"y":1},"o":{"x":0.26,"y":0.64},"n":"0p48_1_0p26_0p64","t":22,"s":[18.349,19.092,0],"e":[123.75,-74.5,0],"to":[29.3167953491211,-73.5986480712891,0],"ti":[-23.5667953491211,48.8486442565918,0]},{"t":113}],"ix":2},"a":{"a":0,"k":[13,8.5,0],"ix":1},"s":{"a":1,"k":[{"i":{"x":[0.058,0.058,0.667],"y":[1,1,1]},"o":{"x":[0,0,0.333],"y":[0,0,0]},"n":["0p058_1_0_0","0p058_1_0_0","0p667_1_0p333_0"],"t":22,"s":[0,0,100],"e":[100,100,100]},{"i":{"x":[1,1,0.667],"y":[1,1,1]},"o":{"x":[0.809,0.809,0.333],"y":[0,0,0]},"n":["1_1_0p809_0","1_1_0p809_0","0p667_1_0p333_0"],"t":54,"s":[100,100,100],"e":[0,0,100]},{"t":115}],"ix":6}},"ao":0,"ip":9,"op":240,"st":9,"bm":0},{"ddd":0,"ind":22,"ty":2,"nm":"4.png","cl":"png","parent":4,"refId":"image_5","sr":1,"ks":{"o":{"a":1,"k":[{"i":{"x":[0.833],"y":[0.833]},"o":{"x":[0.167],"y":[0.167]},"n":["0p833_0p833_0p167_0p167"],"t":0,"s":[0],"e":[100]},{"i":{"x":[0.833],"y":[0.833]},"o":{"x":[0.167],"y":[0.167]},"n":["0p833_0p833_0p167_0p167"],"t":10,"s":[100],"e":[100]},{"i":{"x":[0.833],"y":[0.833]},"o":{"x":[0.167],"y":[0.167]},"n":["0p833_0p833_0p167_0p167"],"t":60,"s":[100],"e":[0]},{"t":71}],"ix":11},"r":{"a":0,"k":0,"ix":10},"p":{"a":0,"k":[42.5,-57,0],"ix":2},"a":{"a":0,"k":[7.5,7.5,0],"ix":1},"s":{"a":1,"k":[{"i":{"x":[0.058,0.058,0.667],"y":[1,1,1]},"o":{"x":[0,0,0.333],"y":[0,0,0]},"n":["0p058_1_0_0","0p058_1_0_0","0p667_1_0p333_0"],"t":0,"s":[0,0,100],"e":[100,100,100]},{"i":{"x":[1,1,0.667],"y":[1,1,1]},"o":{"x":[0.809,0.809,0.333],"y":[0,0,0]},"n":["1_1_0p809_0","1_1_0p809_0","0p667_1_0p333_0"],"t":36,"s":[100,100,100],"e":[0,0,100]},{"t":58}],"ix":6}},"ao":0,"ip":0,"op":240,"st":0,"bm":0},{"ddd":0,"ind":23,"ty":2,"nm":"10.png","cl":"png","parent":4,"refId":"image_6","sr":1,"ks":{"o":{"a":1,"k":[{"i":{"x":[0.833],"y":[0.833]},"o":{"x":[0.167],"y":[0.167]},"n":["0p833_0p833_0p167_0p167"],"t":10,"s":[0],"e":[100]},{"i":{"x":[0.833],"y":[0.833]},"o":{"x":[0.167],"y":[0.167]},"n":["0p833_0p833_0p167_0p167"],"t":20,"s":[100],"e":[100]},{"i":{"x":[0.833],"y":[0.833]},"o":{"x":[0.167],"y":[0.167]},"n":["0p833_0p833_0p167_0p167"],"t":60,"s":[100],"e":[0]},{"t":71}],"ix":11},"r":{"a":0,"k":0,"ix":10},"p":{"a":1,"k":[{"i":{"x":0.48,"y":1},"o":{"x":0.26,"y":0.813},"n":"0p48_1_0p26_0p813","t":10,"s":[-32.469,62.624,0],"e":[-78,49,0],"to":[-7.58856201171875,-2.27059435844421,0],"ti":[7.58856201171875,2.27059435844421,0]},{"t":71}],"ix":2},"a":{"a":0,"k":[14.5,10.5,0],"ix":1},"s":{"a":1,"k":[{"i":{"x":[0.833,0.833,0.833],"y":[0.833,0.833,0.833]},"o":{"x":[0.167,0.167,0.167],"y":[0.167,0.167,0.167]},"n":["0p833_0p833_0p167_0p167","0p833_0p833_0p167_0p167","0p833_0p833_0p167_0p167"],"t":48,"s":[100,100,100],"e":[30,30,100]},{"t":71}],"ix":6}},"ao":0,"ip":0,"op":240,"st":0,"bm":0},{"ddd":0,"ind":24,"ty":2,"nm":"1.png","cl":"png","parent":4,"refId":"image_7","sr":1,"ks":{"o":{"a":1,"k":[{"i":{"x":[0.833],"y":[0.833]},"o":{"x":[0.167],"y":[0.167]},"n":["0p833_0p833_0p167_0p167"],"t":8,"s":[0],"e":[100]},{"i":{"x":[0.833],"y":[0.833]},"o":{"x":[0.167],"y":[0.167]},"n":["0p833_0p833_0p167_0p167"],"t":20,"s":[100],"e":[100]},{"i":{"x":[0.833],"y":[0.833]},"o":{"x":[0.167],"y":[0.167]},"n":["0p833_0p833_0p167_0p167"],"t":69,"s":[100],"e":[0]},{"t":79}],"ix":11},"r":{"a":0,"k":0,"ix":10},"p":{"a":1,"k":[{"i":{"x":0.833,"y":0.833},"o":{"x":0.167,"y":0.167},"n":"0p833_0p833_0p167_0p167","t":8,"s":[45.843,20.644,0],"e":[104.343,-9.356,0],"to":[9.75,-5,0],"ti":[-9.75,5,0]},{"t":79}],"ix":2},"a":{"a":0,"k":[19.5,22.5,0],"ix":1},"s":{"a":1,"k":[{"i":{"x":[0.058,0.058,0.667],"y":[1,1,1]},"o":{"x":[0,0,0.333],"y":[0,0,0]},"n":["0p058_1_0_0","0p058_1_0_0","0p667_1_0p333_0"],"t":8,"s":[0,0,100],"e":[70,70,100]},{"i":{"x":[1,1,0.667],"y":[1,1,1]},"o":{"x":[0.809,0.809,0.333],"y":[0,0,0]},"n":["1_1_0p809_0","1_1_0p809_0","0p667_1_0p333_0"],"t":44,"s":[70,70,100],"e":[0,0,100]},{"t":79}],"ix":6}},"ao":0,"ip":8,"op":240,"st":8,"bm":0},{"ddd":0,"ind":25,"ty":2,"nm":"1.png","cl":"png","parent":4,"refId":"image_7","sr":1,"ks":{"o":{"a":1,"k":[{"i":{"x":[0.833],"y":[0.833]},"o":{"x":[0.167],"y":[0.167]},"n":["0p833_0p833_0p167_0p167"],"t":18,"s":[0],"e":[100]},{"i":{"x":[0.833],"y":[0.833]},"o":{"x":[0.167],"y":[0.167]},"n":["0p833_0p833_0p167_0p167"],"t":30,"s":[100],"e":[100]},{"i":{"x":[0.833],"y":[0.833]},"o":{"x":[0.167],"y":[0.167]},"n":["0p833_0p833_0p167_0p167"],"t":79,"s":[100],"e":[0]},{"t":89}],"ix":11},"r":{"a":0,"k":0,"ix":10},"p":{"a":1,"k":[{"i":{"x":0.833,"y":0.833},"o":{"x":0.167,"y":0.167},"n":"0p833_0p833_0p167_0p167","t":18,"s":[-65.657,-16.356,0],"e":[-91.157,-37.356,0],"to":[-4.25,-3.5,0],"ti":[4.25,3.5,0]},{"t":89}],"ix":2},"a":{"a":0,"k":[19.5,22.5,0],"ix":1},"s":{"a":1,"k":[{"i":{"x":[0.058,0.058,0.667],"y":[1,1,1]},"o":{"x":[0,0,0.333],"y":[0,0,0]},"n":["0p058_1_0_0","0p058_1_0_0","0p667_1_0p333_0"],"t":18,"s":[0,0,100],"e":[100,100,100]},{"i":{"x":[1,1,0.667],"y":[1,1,1]},"o":{"x":[0.809,0.809,0.333],"y":[0,0,0]},"n":["1_1_0p809_0","1_1_0p809_0","0p667_1_0p333_0"],"t":54,"s":[100,100,100],"e":[0,0,100]},{"t":89}],"ix":6}},"ao":0,"ip":18,"op":240,"st":18,"bm":0},{"ddd":0,"ind":26,"ty":2,"nm":"1.png","cl":"png","parent":4,"refId":"image_7","sr":1,"ks":{"o":{"a":1,"k":[{"i":{"x":[0.833],"y":[0.833]},"o":{"x":[0.167],"y":[0.167]},"n":["0p833_0p833_0p167_0p167"],"t":2,"s":[0],"e":[100]},{"i":{"x":[0.833],"y":[0.833]},"o":{"x":[0.167],"y":[0.167]},"n":["0p833_0p833_0p167_0p167"],"t":11,"s":[100],"e":[100]},{"i":{"x":[0.833],"y":[0.833]},"o":{"x":[0.167],"y":[0.167]},"n":["0p833_0p833_0p167_0p167"],"t":52,"s":[100],"e":[0]},{"t":63}],"ix":11},"r":{"a":0,"k":0,"ix":10},"p":{"a":1,"k":[{"i":{"x":0.48,"y":1},"o":{"x":0.076,"y":1},"n":"0p48_1_0p076_1","t":2,"s":[-54.267,-42.926,0],"e":[-64.75,-60.25,0],"to":[-1.74722540378571,-2.88732409477234,0],"ti":[1.74722540378571,2.88732409477234,0]},{"t":63}],"ix":2},"a":{"a":0,"k":[19.5,22.5,0],"ix":1},"s":{"a":1,"k":[{"i":{"x":[0.058,0.058,0.667],"y":[1,1,1]},"o":{"x":[0,0,0.333],"y":[0,0,0]},"n":["0p058_1_0_0","0p058_1_0_0","0p667_1_0p333_0"],"t":2,"s":[0,0,100],"e":[60,60,100]},{"i":{"x":[1,1,0.667],"y":[1,1,1]},"o":{"x":[0.809,0.809,0.333],"y":[0,0,0]},"n":["1_1_0p809_0","1_1_0p809_0","0p667_1_0p333_0"],"t":34,"s":[60,60,100],"e":[0,0,100]},{"t":62}],"ix":6}},"ao":0,"ip":2,"op":240,"st":2,"bm":0},{"ddd":0,"ind":27,"ty":2,"nm":"19.png","cl":"png","parent":4,"refId":"image_8","sr":1,"ks":{"o":{"a":1,"k":[{"i":{"x":[0.833],"y":[0.833]},"o":{"x":[0.167],"y":[0.167]},"n":["0p833_0p833_0p167_0p167"],"t":0,"s":[0],"e":[100]},{"t":13}],"ix":11},"r":{"a":1,"k":[{"i":{"x":[0.48],"y":[1]},"o":{"x":[0.26],"y":[1]},"n":["0p48_1_0p26_1"],"t":0,"s":[-10],"e":[0]},{"t":38}],"ix":10},"p":{"a":1,"k":[{"i":{"x":0.48,"y":1},"o":{"x":0.195,"y":1},"n":"0p48_1_0p195_1","t":0,"s":[63.25,81.5,0],"e":[99.5,80.25,0],"to":[6.04166650772095,-0.20833332836628,0],"ti":[-6.04166650772095,0.20833332836628,0]},{"t":38}],"ix":2},"a":{"a":0,"k":[29,23,0],"ix":1},"s":{"a":0,"k":[100,100,100],"ix":6}},"ao":0,"ip":0,"op":240,"st":0,"bm":0},{"ddd":0,"ind":28,"ty":2,"nm":"7.png","cl":"png","parent":4,"refId":"image_9","sr":1,"ks":{"o":{"a":1,"k":[{"i":{"x":[0.833],"y":[0.833]},"o":{"x":[0.167],"y":[0.167]},"n":["0p833_0p833_0p167_0p167"],"t":0,"s":[0],"e":[100]},{"t":13}],"ix":11},"r":{"a":1,"k":[{"i":{"x":[0.48],"y":[1]},"o":{"x":[0.26],"y":[1]},"n":["0p48_1_0p26_1"],"t":0,"s":[90],"e":[134.077]},{"t":38}],"ix":10},"p":{"a":1,"k":[{"i":{"x":0.48,"y":1},"o":{"x":0.26,"y":1},"n":"0p48_1_0p26_1","t":0,"s":[26,79.75,0],"e":[44.75,81.75,0],"to":[3.125,0.33333334326744,0],"ti":[-3.125,-0.33333334326744,0]},{"t":38}],"ix":2},"a":{"a":0,"k":[21.5,19.5,0],"ix":1},"s":{"a":0,"k":[100,100,100],"ix":6}},"ao":0,"ip":0,"op":240,"st":0,"bm":0},{"ddd":0,"ind":29,"ty":2,"nm":"8.png","cl":"png","parent":4,"refId":"image_10","sr":1,"ks":{"o":{"a":1,"k":[{"i":{"x":[0.833],"y":[0.833]},"o":{"x":[0.167],"y":[0.167]},"n":["0p833_0p833_0p167_0p167"],"t":0,"s":[0],"e":[100]},{"i":{"x":[0.833],"y":[0.833]},"o":{"x":[0.167],"y":[0.167]},"n":["0p833_0p833_0p167_0p167"],"t":13,"s":[100],"e":[100]},{"t":38}],"ix":11},"r":{"a":1,"k":[{"i":{"x":[0.48],"y":[1]},"o":{"x":[0.26],"y":[1]},"n":["0p48_1_0p26_1"],"t":0,"s":[-147],"e":[-119]},{"t":38}],"ix":10},"p":{"a":1,"k":[{"i":{"x":0.48,"y":1},"o":{"x":0.26,"y":1},"n":"0p48_1_0p26_1","t":0,"s":[-58,87.5,0],"e":[-86,81,0],"to":[-4.66666650772095,-1.08333337306976,0],"ti":[4.66666650772095,1.08333337306976,0]},{"t":38}],"ix":2},"a":{"a":0,"k":[26,13,0],"ix":1},"s":{"a":0,"k":[100,100,100],"ix":6}},"ao":0,"ip":0,"op":240,"st":0,"bm":0},{"ddd":0,"ind":30,"ty":2,"nm":"8.png","cl":"png","parent":4,"refId":"image_10","sr":1,"ks":{"o":{"a":1,"k":[{"i":{"x":[0.833],"y":[0.833]},"o":{"x":[0.167],"y":[0.167]},"n":["0p833_0p833_0p167_0p167"],"t":0,"s":[0],"e":[100]},{"i":{"x":[0.833],"y":[0.833]},"o":{"x":[0.167],"y":[0.167]},"n":["0p833_0p833_0p167_0p167"],"t":13,"s":[100],"e":[100]},{"t":38}],"ix":11},"r":{"a":1,"k":[{"i":{"x":[0.48],"y":[1]},"o":{"x":[0.26],"y":[1]},"n":["0p48_1_0p26_1"],"t":0,"s":[-17],"e":[0]},{"t":38}],"ix":10},"p":{"a":1,"k":[{"i":{"x":0.48,"y":1},"o":{"x":0.26,"y":1},"n":"0p48_1_0p26_1","t":0,"s":[-23,87.75,0],"e":[-30.5,81.5,0],"to":[-1.25,-1.04166662693024,0],"ti":[1.25,1.04166662693024,0]},{"t":38}],"ix":2},"a":{"a":0,"k":[26,13,0],"ix":1},"s":{"a":0,"k":[100,100,100],"ix":6}},"ao":0,"ip":0,"op":240,"st":0,"bm":0},{"ddd":0,"ind":31,"ty":2,"nm":"8.png","cl":"png","parent":4,"refId":"image_10","sr":1,"ks":{"o":{"a":1,"k":[{"i":{"x":[0.833],"y":[0.833]},"o":{"x":[0.167],"y":[0.167]},"n":["0p833_0p833_0p167_0p167"],"t":0,"s":[0],"e":[100]},{"i":{"x":[0.833],"y":[0.833]},"o":{"x":[0.167],"y":[0.167]},"n":["0p833_0p833_0p167_0p167"],"t":13,"s":[100],"e":[100]},{"t":38}],"ix":11},"r":{"a":1,"k":[{"i":{"x":[0.48],"y":[1]},"o":{"x":[0.26],"y":[1]},"n":["0p48_1_0p26_1"],"t":0,"s":[10],"e":[0]},{"t":38}],"ix":10},"p":{"a":0,"k":[-9.5,91,0],"ix":2},"a":{"a":0,"k":[26,13,0],"ix":1},"s":{"a":0,"k":[100,100,100],"ix":6}},"ao":0,"ip":0,"op":240,"st":0,"bm":0},{"ddd":0,"ind":32,"ty":2,"nm":"888.png","cl":"png","parent":4,"refId":"image_11","sr":1,"ks":{"o":{"a":1,"k":[{"i":{"x":[0.833],"y":[0.833]},"o":{"x":[0.167],"y":[0.167]},"n":["0p833_0p833_0p167_0p167"],"t":0,"s":[0],"e":[100]},{"i":{"x":[0.833],"y":[0.833]},"o":{"x":[0.167],"y":[0.167]},"n":["0p833_0p833_0p167_0p167"],"t":10,"s":[100],"e":[100]},{"t":82}],"ix":11},"r":{"a":1,"k":[{"i":{"x":[0.342],"y":[1]},"o":{"x":[0],"y":[0]},"n":["0p342_1_0_0"],"t":0,"s":[-27],"e":[5]},{"t":73}],"ix":10},"p":{"a":1,"k":[{"i":{"x":0.48,"y":1},"o":{"x":0.152,"y":1},"n":"0p48_1_0p152_1","t":0,"s":[1,107.25,0],"e":[1,80,0],"to":[0,-4.54166650772095,0],"ti":[0,4.54166650772095,0]},{"t":79}],"ix":2},"a":{"a":0,"k":[64.5,87.318,0],"ix":1},"s":{"a":1,"k":[{"i":{"x":[0.14,0.14,0.667],"y":[1,1,1]},"o":{"x":[0,0,0.333],"y":[0,0,0]},"n":["0p14_1_0_0","0p14_1_0_0","0p667_1_0p333_0"],"t":0,"s":[50,50,100],"e":[100,100,100]},{"t":36}],"ix":6}},"ao":0,"ip":0,"op":240,"st":0,"bm":0}],"markers":[]}
